Metadata-Version: 2.1
Name: General-distributions-vic-xav
Version: 0.1.1.2
Summary: Gaussian distributions
Author: Victor Rivera
Author-email: victorjavier0716@gmail.com
